tractrix/__init__.py
tractrix/tractrix.py
tractrix-0.1.4.dist-info/LICENSE
tractrix-0.1.4.dist-info/METADATA
tractrix-0.1.4.dist-info/WHEEL
tractrix-0.1.4.dist-info/top_level.txt
tractrix-0.1.4.dist-info/RECORD
