Metadata-Version: 2.1
Name: tractrix
Version: 0.1.4
Summary: A convenient implementation of the tractrix magnetopause
Home-page: https://github.com/connor-obrien888/tractrix
Author: Connor OBrien
Author-email: obrienco@bu.edu
License: MIT
Platform: UNKNOWN
Classifier: Programming Language :: Python :: 3
Classifier: License :: OSI Approved :: MIT License
Classifier: Operating System :: OS Independent
Requires-Dist: numpy
